{
    "background_colour": "ff24273a",
    "border_colour": "ff363a4f",
    "buttons": {
        "hover": {
            "background": "ff494d64",
            "border": "ff363a4f"
        },
        "normal": {
            "background": "ff3b4261",
            "border": "ff363a4f"
        },
        "pressed": {
            "background": "ff5b6078",
            "border": "ff363a4f"
        }
    },
    "cards": {
        "common": {
            "normal": "ff3b4261"
        },
        "nohammer": {
            "normal": "ff7e88aa"
        },
        "nosac": {
            "normal": "ff585b70"
        },
        "rare": {
            "normal": "ff4c566a"
        },
        "rns": {
            "normal": "ff8087a2"
        }
    },
    "edit_background_colour": "ff24273a",
    "pixart_colour": "ffcad3f5",
    "text_colour": "ffcad3f5"
}
